tqsim/__init__.py
tqsim/circuit.py
tqsim/config.py
tqsim/lib/basis_generator.py
tqsim/lib/drawer.py
tqsim/lib/drawer_anyon.py
tqsim/lib/operator_generator.py
tqsim/lib/utils.py
tqsim-0.0.2.dist-info/LICENSE
tqsim-0.0.2.dist-info/WHEEL
tqsim-0.0.2.dist-info/METADATA
tqsim-0.0.2.dist-info/RECORD
