Metadata-Version: 2.1
Name: tqsim
Version: 0.0.2
Summary: TQSim is a Topological Quantum Computing simulator based on Anyon models
Home-page: https://github.com/Constantine-Quantum-Tech/tqsim
License: Apache-2.0
Keywords: topological quantum computing,quantum,quantum computing,anyons,simulator
Author: CQTech.org
Author-email: constantinequantumtech@gmail.com
Requires-Python: >=3.8,<4.0
Classifier: License :: OSI Approved :: Apache Software License
Classifier: Programming Language :: Python :: 3
Classifier: Programming Language :: Python :: 3.8
Classifier: Programming Language :: Python :: 3.9
Classifier: Programming Language :: Python :: 3.10
Classifier: Programming Language :: Python :: 3.11
Requires-Dist: matplotlib (>=3.6.1,<4.0.0)
Requires-Dist: numpy (>=1.23.4,<2.0.0)
Project-URL: Repository, https://github.com/Constantine-Quantum-Tech/tqsim
